README.md
list_prs
print_stats
setup.cfg
setup.py
pr_analyzer/__init__.py
pr_analyzer/common.py
pr_analyzer/version.py
pr_analyzer.egg-info/PKG-INFO
pr_analyzer.egg-info/SOURCES.txt
pr_analyzer.egg-info/dependency_links.txt
pr_analyzer.egg-info/requires.txt
pr_analyzer.egg-info/top_level.txt
pr_analyzer/adapters/__init__.py
pr_analyzer/adapters/github_adapter.py
pr_analyzer/application/__init__.py
pr_analyzer/application/model.py
pr_analyzer/application/pr_analyzer.py