Metadata-Version: 2.1
Name: pr-analyzer
Version: 0.1.3
Summary: Small CLI to analyze PRs on the GitHub
Home-page: http://packages.python.org/pr_analyzer
Author: Alexander Pushkarev
Author-email: alexspush@gmail.com
License: MIT
Platform: UNKNOWN
